times2/__init__.py
times2/version.py
times2-0.9.dist-info/AUTHORS
times2-0.9.dist-info/LICENSE
times2-0.9.dist-info/METADATA
times2-0.9.dist-info/WHEEL
times2-0.9.dist-info/top_level.txt
times2-0.9.dist-info/RECORD
